setup.py
scripts/run_tkprocess.py
tkprocess/__init__.py
tkprocess/tkprocess.py
tkprocess/tksettings.py
tkprocess.egg-info/PKG-INFO
tkprocess.egg-info/SOURCES.txt
tkprocess.egg-info/dependency_links.txt
tkprocess.egg-info/top_level.txt
tkprocess/core/__init__.py
tkprocess/core/backwardcompat.py
tkprocess/core/dump.py
tkprocess/core/settings.py
tkprocess/core/tkprop.py