Metadata-Version: 1.1
Name: tkprocess
Version: 0.1
Summary: A subprocess application based on Tk.
Home-page: http://github.com/lishnih/tkprocess
Author: Stan
Author-email: lishnih@gmail.com
License: UNKNOWN
Keywords: Tk,subprocess,threading
Platform: any
Classifier: Development Status :: 4 - Beta
Classifier: Intended Audience :: Developers
Classifier: License :: Public Domain
Classifier: Operating System :: OS Independent
Classifier: Programming Language :: Python
Classifier: Programming Language :: Python :: 2.6
Classifier: Programming Language :: Python :: 3.3
Classifier: Topic :: Utilities
